CHANGES.txt
README.txt
bootstrap.py
buildout.cfg
setup.py
buildout/__init__.py
buildout.threatlevel.egg-info/PKG-INFO
buildout.threatlevel.egg-info/SOURCES.txt
buildout.threatlevel.egg-info/dependency_links.txt
buildout.threatlevel.egg-info/entry_points.txt
buildout.threatlevel.egg-info/namespace_packages.txt
buildout.threatlevel.egg-info/not-zip-safe
buildout.threatlevel.egg-info/requires.txt
buildout.threatlevel.egg-info/top_level.txt
buildout/threatlevel/__init__.py