Metadata-Version: 1.0
Name: buildout.threatlevel
Version: 1.0
Summary: A zc.buildout extension that reports the current global buildout threat level
Home-page: http://svn.plone.org/svn/collective/buildout/buildout.threatlevel
Author: David Glick
Author-email: dglick@gmail.com
License: GPL
Keywords: buildout extension threat
Platform: UNKNOWN
Classifier: Framework :: Buildout
Classifier: Intended Audience :: Developers
Classifier: Topic :: Software Development :: Build Tools
Classifier: Topic :: Software Development :: Libraries :: Python Modules
